COPYING
MANIFEST.in
README.rst
bootstrap-buildout.py
buildout.cfg
develop.cfg
requirements.txt
setup.py
version.txt
bob/__init__.py
bob.db.bio_filelist.egg-info/PKG-INFO
bob.db.bio_filelist.egg-info/SOURCES.txt
bob.db.bio_filelist.egg-info/dependency_links.txt
bob.db.bio_filelist.egg-info/entry_points.txt
bob.db.bio_filelist.egg-info/not-zip-safe
bob.db.bio_filelist.egg-info/requires.txt
bob.db.bio_filelist.egg-info/top_level.txt
bob/db/__init__.py
bob/db/bio_filelist/__init__.py
bob/db/bio_filelist/driver.py
bob/db/bio_filelist/models.py
bob/db/bio_filelist/query.py
bob/db/bio_filelist/test.py
bob/db/bio_filelist/example_fl/data/model4_session1_sample2.pos
bob/db/bio_filelist/example_fl/dev/for_models.lst
bob/db/bio_filelist/example_fl/dev/for_probes.lst
bob/db/bio_filelist/example_fl/dev/for_scores.lst
bob/db/bio_filelist/example_fl/dev/for_tnorm.lst
bob/db/bio_filelist/example_fl/dev/for_znorm.lst
bob/db/bio_filelist/example_fl/eval/for_models.lst
bob/db/bio_filelist/example_fl/eval/for_probes.lst
bob/db/bio_filelist/example_fl/eval/for_scores.lst
bob/db/bio_filelist/example_fl/eval/for_tnorm.lst
bob/db/bio_filelist/example_fl/eval/for_znorm.lst
bob/db/bio_filelist/example_fl/norm/train_optional_world_1.lst
bob/db/bio_filelist/example_fl/norm/train_optional_world_2.lst
bob/db/bio_filelist/example_fl/norm/train_world.lst
doc/conf.py
doc/guide.rst
doc/index.rst
doc/py_api.rst